cy7c65211/__init__.py
cy7c65211/common.py
cy7c65211/device.py
cy7c65211/header.py
nrf24/__init__.py
nrf24/chip.py
nrf24/register.py
ucdev/__init__.py
ucdev/ad9850.py
ucdev/common.py
ucdev/hmc5883.py
ucdev/mpu6050.py
ucdev/nrf24.py
ucdev/register.py
ucdev/si4702.py
ucdev-0.0.3.dist-info/METADATA
ucdev-0.0.3.dist-info/RECORD
ucdev-0.0.3.dist-info/WHEEL
ucdev-0.0.3.dist-info/top_level.txt
