Metadata-Version: 2.1
Name: ucdev
Version: 0.0.3
Summary: Library to access various I2C/SPI/GPIO-accessible chips over Cypress CY7C65211/3/5 USB-to-UART/I2C/SPI/GPIO bridge.
Home-page: https://github.com/tai/python-ucdev/
Author: Taisuke Yamada
Author-email: tai@remove-if-not-spam.rakugaki.org
License: MIT
Platform: UNKNOWN
Classifier: License :: OSI Approved :: MIT License
Classifier: Intended Audience :: Developers
Classifier: Programming Language :: Python :: 2
Classifier: Programming Language :: Python :: 2.7
Classifier: Programming Language :: Python :: 3
Classifier: Topic :: Scientific/Engineering
Classifier: Topic :: Software Development :: Embedded Systems
Classifier: Topic :: System :: Hardware
Requires-Dist: bitstring
Requires-Dist: cffi
Requires-Dist: IPython
